mgktools/__init__.py
mgktools/data/__init__.py
mgktools/data/data.py
mgktools/data/split.py
mgktools/evaluators/__init__.py
mgktools/evaluators/cross_validation.py
mgktools/evaluators/metric.py
mgktools/exe/__init__.py
mgktools/exe/args.py
mgktools/exe/model.py
mgktools/exe/run.py
mgktools/features_mol/__init__.py
mgktools/features_mol/features_generators.py
mgktools/features_mol/utils.py
mgktools/graph/__init__.py
mgktools/graph/emodes.dat
mgktools/graph/from_rdkit.py
mgktools/graph/hashgraph.py
mgktools/hyperparameters/__init__.py
mgktools/hyperparameters/optuna.py
mgktools/hyperparameters/configs/additive-msnorm.json
mgktools/hyperparameters/configs/additive-norm.json
mgktools/hyperparameters/configs/additive-pnorm.json
mgktools/hyperparameters/configs/additive.json
mgktools/hyperparameters/configs/dot_product.json
mgktools/hyperparameters/configs/product-msnorm.json
mgktools/hyperparameters/configs/product-norm.json
mgktools/hyperparameters/configs/product-pnorm.json
mgktools/hyperparameters/configs/product.json
mgktools/hyperparameters/configs/rbf.json
mgktools/interpret/__init__.py
mgktools/interpret/interpret.py
mgktools/interpret/subgraph.py
mgktools/interpret/subgraph_search.py
mgktools/interpret/utils.py
mgktools/kernels/FeatureKernel.py
mgktools/kernels/GraphKernel.py
mgktools/kernels/HybridKernel.py
mgktools/kernels/PreComputed.py
mgktools/kernels/__init__.py
mgktools/kernels/base.py
mgktools/kernels/normalization.py
mgktools/kernels/utils.py
mgktools/models/__init__.py
mgktools/models/classification/__init__.py
mgktools/models/classification/gpc/__init__.py
mgktools/models/classification/gpc/gpc.py
mgktools/models/classification/svm/__init__.py
mgktools/models/classification/svm/svm.py
mgktools/models/regression/__init__.py
mgktools/models/regression/consensus.py
mgktools/models/regression/gpr/__init__.py
mgktools/models/regression/gpr/gpr.py
mgktools/models/regression/scalable/NLE.py
mgktools/models/regression/scalable/__init__.py
mgktools-3.2.0.dist-info/licenses/LICENSE
mgktools-3.2.0.dist-info/METADATA
mgktools-3.2.0.dist-info/WHEEL
mgktools-3.2.0.dist-info/entry_points.txt
mgktools-3.2.0.dist-info/top_level.txt
mgktools-3.2.0.dist-info/RECORD
