Metadata-Version: 2.4
Name: mgktools
Version: 3.2.0
Summary: Marginalized Graph Kernel Library for Molecular Property Prediction
Author-email: Yan Xiang <yan.xiang@duke.edu>
License: MIT
Project-URL: source, https://github.com/xiangyan93/mgktools
Project-URL: PyPi, https://pypi.org/project/mgktools/
Keywords: chemistry,machine learning,molecular property prediction,marginalized graph kernel,drug discovery
Classifier: Programming Language :: Python :: 3
Classifier: Programming Language :: Python :: 3.12
Classifier: License :: OSI Approved :: MIT License
Classifier: Operating System :: OS Independent
Requires-Python: >=3.10
License-File: LICENSE
Requires-Dist: rdkit==2023.9.6
Requires-Dist: descriptastorus==2.6.1
Requires-Dist: numpy==1.26.4
Requires-Dist: mendeleev==0.19.0
Requires-Dist: typed-argument-parser
Requires-Dist: scikit-learn
Requires-Dist: rxntools
Requires-Dist: optuna
Requires-Dist: hyperopt
Requires-Dist: ipython
Requires-Dist: pytest
Dynamic: license-file
